recette/__init__.py
recette/steps.py
recette/types.py
recette/utils.py
recette-0.2.1.dist-info/LICENSE
recette-0.2.1.dist-info/METADATA
recette-0.2.1.dist-info/WHEEL
recette-0.2.1.dist-info/top_level.txt
recette-0.2.1.dist-info/RECORD
