Metadata-Version: 2.1
Name: recette
Version: 0.2.1
Summary: Data preprocessing utilities on top of pandas.
Home-page: https://github.com/pennacchio/recette
Author: Alan Pennacchio
Author-email: alanpennacchio@icloud.com
License: UNKNOWN
Platform: UNKNOWN
Classifier: Programming Language :: Python :: 3
Classifier: License :: OSI Approved :: MIT License
Classifier: Operating System :: OS Independent
Requires-Python: >=3.6
Requires-Dist: pandas (>=1.0.3)
Requires-Dist: toolz (>=0.10.0)
